flame/__init__.py
flame/apply.py
flame/build.py
flame/config.yaml
flame/context.py
flame/control.py
flame/flame-ws.py
flame/flame.py
flame/flame_cmd.py
flame/flame_scr.py
flame/idata.py
flame/learn.py
flame/manage.py
flame/odata.py
flame/predict-ws.py
flame/predict.py
flame/chem/__init__.py
flame/chem/compute_md.py
flame/chem/convert_3d.py
flame/chem/sdfileutils.py
flame/children/__init__.py
flame/children/apply_child.py
flame/children/idata_child.py
flame/children/learn_child.py
flame/children/odata_child.py
flame/children/parameters.yaml
flame/stats/FDD.py
flame/stats/GNB.py
flame/stats/PLSDA.py
flame/stats/PLSR.py
flame/stats/RF.py
flame/stats/SVM.py
flame/stats/__init__.py
flame/stats/base_model.py
flame/stats/feature_selection.py
flame/stats/imbalance.py
flame/stats/model_validation.py
flame/stats/scale.py
flame/util/__init__.py
flame/util/config.py
flame/util/utils.py
flame-0.1.dist-info/LICENSE
flame-0.1.dist-info/METADATA
flame-0.1.dist-info/WHEEL
flame-0.1.dist-info/dependency_links.txt
flame-0.1.dist-info/entry_points.txt
flame-0.1.dist-info/top_level.txt
flame-0.1.dist-info/RECORD
