Metadata-Version: 2.1
Name: flame
Version: 0.1
Summary: UNKNOWN
Home-page: https://github.com/phi-grib/flame
Author: Manuel Pastor, Biel Stela, Jose Carlos Gomez
Author-email: manuel.pastor@upf.edu
License: GNU GPLv3 or posterior
Download-URL: https://github.com/phi-grib/flame.git
Platform: UNKNOWN
Requires-Dist: standardiser
Requires-Dist: nonconformist
